whatsapp_toolkit/.DS_Store
whatsapp_toolkit/__init__.py
whatsapp_toolkit/async_client.py
whatsapp_toolkit/async_instance.py
whatsapp_toolkit/async_sender.py
whatsapp_toolkit/cli/__init__.py
whatsapp_toolkit/cli/evolution.py
whatsapp_toolkit/cli/main.py
whatsapp_toolkit/cli/utils.py
whatsapp_toolkit/cli/webhook.py
whatsapp_toolkit/client.py
whatsapp_toolkit/devtools/__init__.py
whatsapp_toolkit/devtools/evolution.py
whatsapp_toolkit/devtools/main.py
whatsapp_toolkit/devtools/templates/__init__.py
whatsapp_toolkit/devtools/templates/evo_templates.py
whatsapp_toolkit/devtools/templates/webhook_templates.py
whatsapp_toolkit/devtools/utils.py
whatsapp_toolkit/devtools/webhook.py
whatsapp_toolkit/instance.py
whatsapp_toolkit/media.py
whatsapp_toolkit/pc.jpeg
whatsapp_toolkit/schemas.py
whatsapp_toolkit/sender.py
whatsapp_toolkit/utils/__init__.py
whatsapp_toolkit/utils/audio.py
whatsapp_toolkit/utils/utils.py
whatsapp_toolkit/webhook/__init__.py
whatsapp_toolkit/webhook/dispatcher.py
whatsapp_toolkit/webhook/events.py
whatsapp_toolkit/webhook/message_type.py
whatsapp_toolkit/webhook/router.py
whatsapp_toolkit/webhook/schemas/__init__.py
whatsapp_toolkit/webhook/schemas/conection.py
whatsapp_toolkit/webhook/schemas/message.py
whatsapp_toolkit/webhook/utils.py
whatsapp_toolkit-1.9.2.dist-info/WHEEL
whatsapp_toolkit-1.9.2.dist-info/entry_points.txt
whatsapp_toolkit-1.9.2.dist-info/METADATA
whatsapp_toolkit-1.9.2.dist-info/RECORD
