Metadata-Version: 2.3
Name: whatsapp-toolkit
Version: 1.9.2
Summary: Una biblioteca para interactuar con la API de WhatsApp desde Python usando Evolution API
Author: Fernando Leon Franco
Author-email: Fernando Leon Franco <fernanlee2131@gmail.com>
License: MIT
Classifier: License :: OSI Approved :: MIT License
Classifier: Programming Language :: Python :: 3.10
Classifier: Programming Language :: Python :: 3.11
Classifier: Programming Language :: Python :: 3.12
Classifier: Programming Language :: Python :: 3.13
Classifier: Operating System :: OS Independent
Requires-Dist: colorstreak>=2.1.3
Requires-Dist: fastapi>=0.124.4
Requires-Dist: groq>=1.0.0
Requires-Dist: httpx>=0.28.1
Requires-Dist: jinja2>=3.1.6
Requires-Dist: pillow>=12.0.0
Requires-Dist: piper-tts>=1.3.0
Requires-Dist: platformdirs>=4.5.1
Requires-Dist: pydantic[email]>=2.12.5
Requires-Dist: pymongo>=4.15.5
Requires-Dist: python-dotenv>=1.2.1
Requires-Dist: qrcode>=8.2
Requires-Dist: reportlab>=4.4.6
Requires-Dist: requests>=2.32.5
Requires-Dist: typer>=0.21.0
Requires-Dist: uvicorn>=0.38.0
Requires-Python: >=3.10
Project-URL: Homepage, https://github.com/epok200/whatsapp_toolkit
Project-URL: Issues, https://github.com/epok200/whatsapp_toolkit/issues
Project-URL: Repository, https://github.com/epok200/whatsapp_toolkit
